README.md
setup.py
agacsayisi/__init__.py
agacsayisi/tree.py
agacsayisi.egg-info/PKG-INFO
agacsayisi.egg-info/SOURCES.txt
agacsayisi.egg-info/dependency_links.txt
agacsayisi.egg-info/top_level.txt