Metadata-Version: 1.0
Name: agacsayisi
Version: 1.1.5
Summary: Miktara göre ağaç sayısı
Home-page: https://github.com/sscok/agac.git
Author: Sevim Çokoğlu
Author-email: sedacokoglu@hotmail.com
License: MIT
Platform: UNKNOWN
